LICENSE
MANIFEST.in
README.md
setup.py
silence_tensorflow/__init__.py
silence_tensorflow/__version__.py
silence_tensorflow/auto.py
silence_tensorflow/silence_tensorflow.py
silence_tensorflow.egg-info/PKG-INFO
silence_tensorflow.egg-info/SOURCES.txt
silence_tensorflow.egg-info/dependency_links.txt
silence_tensorflow.egg-info/requires.txt
silence_tensorflow.egg-info/top_level.txt