Metadata-Version: 2.1
Name: silence-tensorflow
Version: 1.2.2
Summary: Simple python package to shut up Tensorflow warnings and logs.
Home-page: https://github.com/LucaCappelletti94/silence_tensorflow
Author: Luca Cappelletti
Author-email: cappelletti.luca94@gmail.com
License: MIT
Platform: UNKNOWN
Classifier: Development Status :: 5 - Production/Stable
Classifier: License :: OSI Approved :: MIT License
Classifier: Programming Language :: Python :: 3
Provides-Extra: test
License-File: LICENSE
